testcontainers/google/__init__.py
testcontainers/google/pubsub.py
tests/test_google.py
testcontainers_gcp-0.0.1rc1.dist-info/METADATA
testcontainers_gcp-0.0.1rc1.dist-info/WHEEL
testcontainers_gcp-0.0.1rc1.dist-info/top_level.txt
testcontainers_gcp-0.0.1rc1.dist-info/RECORD
